DECODER/decoder4x16.v

module decoder4x16(input [3:0]in, input enable, output [15:0]out);
wire enable_low= enable & ~in[3]; 
wire enable_high= enable & in[3];
decoder3x8 d1(.in(in[2:0]), .enable(enable_low), .out(out[7:0]));
decoder3x8 d2(.in(in[2:0]), .enable(enable_high), .out(out[15:8]));
endmodule
module decoder3x8(
    input wire [2:0] in,      // 3-bit input
    input wire enable,        // Enable signal
    output reg [7:0] out      // 8-bit output (one-hot)
);
    always @(*) begin
        if (enable) begin
            case(in)
                3'b000: out = 8'b00000001;
                3'b001: out = 8'b00000010;
                3'b010: out = 8'b00000100;
                3'b011: out = 8'b00001000;
                3'b100: out = 8'b00010000;
                3'b101: out = 8'b00100000;
                3'b110: out = 8'b01000000;
                3'b111: out = 8'b10000000;
                default: out = 8'b00000000;
            endcase
        end else begin
            out = 8'b00000000;  // All outputs inactive when disabled
        end
    end
endmodule

DECODER/decoder4x16_tb.v
`include "decoder4x16.v"
module decoder4x16_tb;
    reg [3:0] in;
    reg enable;
    wire [15:0] out;
decoder4x16 dut (.in(in),.enable(enable),  .out(out));
 integer i;
 initial begin
        $display("Enable | Input | Output");
        $display("-----------------------------");
        enable = 1'b1;
        for (i = 0; i < 16; i = i + 1) begin
            in = i[3:0];
            #5;
            $display("  %b    | %b  | %b", enable, in, out);
        end
        enable = 1'b0;
        in = 4'b1010; #5;
        $display("  %b    | %b  | %b (Enable Low)", enable, in, out);
        $finish;
    end
    initial begin
        $dumpfile("decoder4x16_tb.vcd");
        $dumpvars(0, decoder4x16_tb);
    end
endmodule

DECODER/decoder4x16_tb.vcd
$date
	Wed May 14 07:00:37 2025
$end
$version
	Icarus Verilog
$end
$timescale
	1s
$end
$scope module decoder4x16_tb $end
$var wire 16 ! out [15:0] $end
$var reg 1 " enable $end
$var integer 32 # i [31:0] $end
$var reg 4 $ in [3:0] $end
$scope module dut $end
$var wire 1 % enable $end
$var wire 1 & enable_high $end
$var wire 1 ' enable_low $end
$var wire 4 ( in [3:0] $end
$var wire 16 ) out [15:0] $end
$scope module d1 $end
$var wire 1 ' enable $end
$var wire 3 * in [2:0] $end
$var reg 8 + out [7:0] $end
$upscope $end
$scope module d2 $end
$var wire 1 & enable $end
$var wire 3 , in [2:0] $end
$var reg 8 - out [7:0] $end
$upscope $end
$upscope $end
$upscope $end
$enddefinitions $end
#0
$dumpvars
b0 -
b0 ,
b1 +
b0 *
b1 )
b0 (
1'
0&
1%
b0 $
b0 #
1"
b1 !
$end
#5
b10 +
b10 !
b10 )
b1 *
b1 ,
b1 $
b1 (
b1 #
#10
b100 +
b100 !
b100 )
b10 *
b10 ,
b10 $
b10 (
b10 #
#15
b1000 +
b1000 !
b1000 )
b11 *
b11 ,
b11 $
b11 (
b11 #
#20
b10000 +
b10000 !
b10000 )
b100 *
b100 ,
b100 $
b100 (
b100 #
#25
b100000 +
b100000 !
b100000 )
b101 *
b101 ,
b101 $
b101 (
b101 #
#30
b1000000 +
b1000000 !
b1000000 )
b110 *
b110 ,
b110 $
b110 (
b110 #
#35
b10000000 +
b10000000 !
b10000000 )
b111 *
b111 ,
b111 $
b111 (
b111 #
#40
0'
b1 -
1&
b0 +
b100000000 !
b100000000 )
b0 *
b0 ,
b1000 $
b1000 (
b1000 #
#45
b10 -
b1000000000 !
b1000000000 )
b1 *
b1 ,
b1001 $
b1001 (
b1001 #
#50
b100 -
b10000000000 !
b10000000000 )
b10 *
b10 ,
b1010 $
b1010 (
b1010 #
#55
b1000 -
b100000000000 !
b100000000000 )
b11 *
b11 ,
b1011 $
b1011 (
b1011 #
#60
b10000 -
b1000000000000 !
b1000000000000 )
b100 *
b100 ,
b1100 $
b1100 (
b1100 #
#65
b100000 -
b10000000000000 !
b10000000000000 )
b101 *
b101 ,
b1101 $
b1101 (
b1101 #
#70
b1000000 -
b100000000000000 !
b100000000000000 )
b110 *
b110 ,
b1110 $
b1110 (
b1110 #
#75
b10000000 -
b1000000000000000 !
b1000000000000000 )
b111 *
b111 ,
b1111 $
b1111 (
b1111 #
#80
b0 -
b0 !
b0 )
b10 *
b10 ,
0&
b1010 $
b1010 (
0"
0%
b10000 #
